strym-1.0.2.dist-info/METADATA
strym-1.0.2.dist-info/WHEEL
strym-1.0.2.dist-info/licenses/LICENSE
strym/DBC_Read_Tools.py
strym/TODO.todo
strym/__init__.py
strym/_core.abi3.so
strym/_core.pyi
strym/config.py
strym/dashboard.py
strym/dbc/honda_pilot_2017.dbc
strym/dbc/nissan_rogue_2021.dbc
strym/dbc/nissan_rogue_experimental.dbc
strym/dbc/toyota_rav4_2019.dbc
strym/dbc/toyota_rav4_2020.dbc
strym/dbc/toyota_rav4_2021.dbc
strym/dbc/toyota_rav4_hybrid.dbc
strym/meta.py
strym/ml/__init__.py
strym/ml/model.py
strym/multimode/__init__.py
strym/multimode/platoons.py
strym/phasespace.py
strym/py.typed
strym/strym.py
strym/strymmap.py
strym/strymread.py
strym/tools.py
strym/utils/__init__.py
strym/utils/log.py
strym/utils/vehicle_utils.py
strym/version
strym-1.0.2.dist-info/RECORD
