Metadata-Version: 2.4
Name: strym
Version: 1.0.2
Requires-Dist: cantools>=40.2.1
Requires-Dist: dotenv>=0.9.9
Requires-Dist: ipykernel>=6.29.5
Requires-Dist: matplotlib>=3.10.3
Requires-Dist: numpy>=2.2.5
Requires-Dist: pandas>=2.2.3
Requires-Dist: plotly>=6.0.1
Requires-Dist: requests>=2.32.3
Requires-Dist: scikit-learn>=1.6.1
Requires-Dist: scipy>=1.15.3
Requires-Dist: seaborn>=0.13.2
Requires-Dist: torch>=2.7.0
Requires-Dist: twine>=6.1.0
Requires-Dist: urllib3>=1.25.11
Requires-Dist: vininfo>=1.8.0
License-File: LICENSE
Summary: A real time CAN data logging and visualization tool to work with USB-CAN Interface
Author-email: Rahul Bhadani <rahulbhadani@email.arizona.edu>
Requires-Python: >=3.12
